setup.py
aiomock/__init__.py
aiomock.egg-info/PKG-INFO
aiomock.egg-info/SOURCES.txt
aiomock.egg-info/dependency_links.txt
aiomock.egg-info/top_level.txt