Metadata-Version: 1.0
Name: aiomock
Version: 0.1.0
Summary: a python mock with async methods
Home-page: https://github.com/nhumrich/aiomock
Author: nhumrich
Author-email: nick@humrich.us
License: MIT
Keywords: asyncio,testing,mock
Platform: UNKNOWN
